ssip/__init__.py
ssip/auto_surgeries.py
ssip/basic_functions.py
ssip/code_examples.py
ssip/coequalisers.py
ssip/distance.py
ssip/lifted_product.py
ssip/merge_result.py
ssip/monic_span_checker.py
ssip/pushouts.py
ssip-0.1.1.dist-info/LICENSE
ssip-0.1.1.dist-info/METADATA
ssip-0.1.1.dist-info/WHEEL
ssip-0.1.1.dist-info/RECORD
