Metadata-Version: 2.1
Name: ssip
Version: 0.1.1
Summary: "Tools to perform surgery with CSS codes"
Author: Alexander Cowtan
Author-email: alexander.cowtan@quantinuum.com
Requires-Python: >=3.10,<4.0
Classifier: Programming Language :: Python :: 3
Classifier: Programming Language :: Python :: 3.10
Classifier: Programming Language :: Python :: 3.11
Classifier: Programming Language :: Python :: 3.12
Requires-Dist: networkx (>=3.3,<4.0)
Requires-Dist: numpy (>=1.26.4,<2.0.0)
Requires-Dist: pytest-cov (>=5.0.0,<6.0.0)
Requires-Dist: z3-solver (>=4.13.0.0,<5.0.0.0)
